{
  "version": "0.1.0",
  "description": "An example Snap written in TypeScript.",
  "proposedName": "ChainSafer Snap",
  "repository": {
    "type": "git",
    "url": "https://github.com/MetaMask/template-snap-monorepo.git"
  },
  "source": {
    "shasum": "4QnLPv8WZqKvRv5hoCRSdaArPQBV2lVuP0VKER91kLk=",
    "location": {
      "npm": {
        "filePath": "dist/bundle.js",
        "iconPath": "images/icon.svg",
        "packageName": "snap",
        "registry": "https://registry.npmjs.org/"
      }
    }
  },
  "initialPermissions": {
    "snap_dialog": {},
    "snap_manageState": {},
    "endowment:rpc": {
      "dapps": true,
      "snaps": false
    },
    "endowment:transaction-insight": {
      "allowTransactionOrigin": true
    },
    "endowment:network-access": {}
  },
  "manifestVersion": "0.1"
}
